{
  "company_website": "https://airudder.com/",
  "countries": [
    "SG",
    "ID",
    "PH",
    "MX",
    "TH",
    "BR",
    "SA",
    "NG",
    "US",
    "VN"
  ],
  "id": "8075333419194821",
  "name": "AIRudder",
  "description": "AIRudder is on a mission to transform your customer engagement by combining the best of artificial intelligence (AI) and human service. Our team has 10+ years of AI experience and a proven track-record of results with 200+ clients across Southeast Asia, India and beyond. AIRudder’s natural language voice AI and text AI assistants take care of repetitive tasks, freeing your agents to delight customers. AIRudder supports all most of the main languages in the world, for example, English, Chinese, Bahasa, Hindi, Tagalog, Bengali, Marathi, Spanish, Thai, Vietnamese, Malay, Korean, Afar, Japanese, Arabic, Portuguese, Urdu, Polish and so on.",
  "diverse_owned_identities": [],
  "facebook_platforms": [
    "WHATSAPP"
  ],
  "focus_areas": [
    "Chatbot, Voicebot",
    "Banking & Finance, Insurance, Ecommerce & Retail, Logistics & Supply Chain ",
    "WhatsApp, Facebook, Instagram"
  ],
  "industries": [
    "AUTOMOTIVE",
    "CONSUMER_PACKAGED_GOODS",
    "ECOMMERCE",
    "FINANCIAL_SERVICES",
    "PROFESSIONAL_SERVICES",
    "RETAIL",
    "TECHNOLOGY"
  ],
  "is_badged": true,
  "language_tags": [
    "en",
    "ar",
    "tl",
    "zh-hans",
    "th",
    "id",
    "pt"
  ],
  "msp_profile_picture": {
    "image": {
      "uri": "https://scontent.fnag7-1.fna.fbcdn.net/v/t39.30808-6/473073341_122180026472120937_2502985620157176726_n.jpg?_nc_cat=103&ccb=1-7&_nc_sid=1e617a&_nc_ohc=rtYy426HZJUQ7kNvwG3E6H6&_nc_oc=AdmsC0hgU84tIiNIwzoMjg8GcvTVcExKP5DgT1RIYEIcZ7X6MgrmHV13FmMoUD8SZf8&_nc_zt=23&_nc_ht=scontent.fnag7-1.fna&_nc_gid=1mYvAsoAjYY5PVO0-3q0qA&oh=00_AffWHuxuvTwj8kdWdxgMIEKfjsrESDXBkqkfEHAthspEgg&oe=68E98F28"
    },
    "id": "122154123038120937"
  },
  "service_models": [
    "SAAS",
    "PROJECT_BASED"
  ],
  "solution_types": [
    "MESSAGING"
  ],
  "solution_subtypes": [],
  "__typename": "MarketingSolutionProvider"
}