{
  "company_website": "https://closingpilot.com/",
  "countries": [
    "MY"
  ],
  "id": "5309891472401831",
  "name": "Closing Pilot Chatbot",
  "description": "An educational platform focusing on Facebook automation and contest marketing. Our strength is turning complex theoretical Facebook marketing into replicable practical steps.",
  "diverse_owned_identities": [],
  "facebook_platforms": [
    "MESSENGER"
  ],
  "focus_areas": [
    "Facebook Messaging Automation ",
    "Facebook Contest Marketing"
  ],
  "industries": [
    "TECHNOLOGY"
  ],
  "is_badged": true,
  "language_tags": [
    "zh-hans"
  ],
  "msp_profile_picture": {
    "image": {
      "uri": "https://scontent.fnag7-1.fna.fbcdn.net/v/t39.30808-6/482082842_670740592304123_1433119616418608412_n.jpg?_nc_cat=106&ccb=1-7&_nc_sid=1e617a&_nc_ohc=5_t0vuwPKSgQ7kNvwHomSJ7&_nc_oc=Adm2qt-mi6rcmDa7BjvjZhD8Lnd5wOO7_og4z-z-KDDz5_tCLfgYiQMd1Z7q97JDM2U&_nc_zt=23&_nc_ht=scontent.fnag7-1.fna&_nc_gid=0fZGfUuktJ1zDFL9CvvsiQ&oh=00_AfdUkWQEc5N0xatbTtPI5OYticcyF5KeU4Y6z1zyl2g9VA&oe=68E9A26F"
    },
    "id": "383593867685465"
  },
  "service_models": [
    "SAAS"
  ],
  "solution_types": [
    "MESSAGING"
  ],
  "solution_subtypes": [],
  "__typename": "MarketingSolutionProvider"
}