{
  "company_website": "https://www.inconcertcx.com/",
  "countries": [
    "MX",
    "ES",
    "AR",
    "CO",
    "PY",
    "DO",
    "EC",
    "US",
    "CR",
    "UY"
  ],
  "id": "7525822927519179",
  "name": "Inconcert",
  "description": "The technological partner that's there throughout your CX transformation. GenAI-powered cloud solutions that help you grow your business.",
  "diverse_owned_identities": [],
  "facebook_platforms": [
    "WHATSAPP"
  ],
  "focus_areas": [
    "Omnichannel SaaS. End-to-End Customer Experience Solution",
    "WhatsApp Business API",
    "Conversational GenAI"
  ],
  "industries": [
    "TECHNOLOGY"
  ],
  "is_badged": true,
  "language_tags": [
    "es",
    "en"
  ],
  "msp_profile_picture": {
    "image": {
      "uri": "https://scontent.fnag7-1.fna.fbcdn.net/v/t39.30808-6/457747685_122176921466199934_5879662054819779245_n.jpg?_nc_cat=105&ccb=1-7&_nc_sid=1e617a&_nc_ohc=GRbGQ02oeFYQ7kNvwG7c5Xf&_nc_oc=AdlYADj35D26NtHQDDrgFelaoqXKm0evW-ltG5hs5rWiEGQ2qef1dekewG1E0IwSyIA&_nc_zt=23&_nc_ht=scontent.fnag7-1.fna&_nc_gid=mU_-KLmWnloN6q_V1o7Q7g&oh=00_Afdck-rID4h8RfdNSnoGZgjH5DoIfUTH5c_dpfNlSs9j0A&oe=68E9A518"
    },
    "id": "122176921460199934"
  },
  "service_models": [
    "SAAS"
  ],
  "solution_types": [
    "MESSAGING"
  ],
  "solution_subtypes": [],
  "__typename": "MarketingSolutionProvider"
}