{
  "company_website": "https://www.nvoip.com.br/",
  "countries": [
    "BR",
    "US",
    "PT",
    "CL",
    "AR",
    "MX",
    "ES"
  ],
  "id": "6628928923879888",
  "name": "Nvoip",
  "description": "A Nvoip conecta empresas e clientes de forma simples através de uma plataforma Omnichannel totalmente self-service, no-code, fácil de usar e que conta com Whatsapp, Telefonia, Chat, Instagram e Messenger, com soluções de automação, voicebot, Chatbots, IA e API.",
  "diverse_owned_identities": [
    "LATINX"
  ],
  "facebook_platforms": [
    "WHATSAPP"
  ],
  "focus_areas": [
    "Atendimento ao Cliente",
    "Vendas",
    "Suporte Técnico"
  ],
  "industries": [
    "GAMING",
    "FINANCIAL_SERVICES",
    "ENTERTAINMENT_AND_MEDIA",
    "ENERGY_AND_UTILITIES",
    "EDUCATION",
    "ECOMMERCE",
    "CONSUMER_PACKAGED_GOODS",
    "AUTOMOTIVE"
  ],
  "is_badged": true,
  "language_tags": [
    "pt",
    "es",
    "es-419",
    "en"
  ],
  "msp_profile_picture": {
    "image": {
      "uri": "https://scontent.fnag7-1.fna.fbcdn.net/v/t39.30808-6/555914691_1858016668400355_9161701416636998616_n.jpg?_nc_cat=110&ccb=1-7&_nc_sid=1e617a&_nc_ohc=_XdfgYnGTKgQ7kNvwHjewoI&_nc_oc=Adm4IY6nPYoVx5qynDvIkxLdWbAMZ-_9NfQ5VGsGdcZ8vqwHmqxuDMw9TIIk-ptGy7o&_nc_zt=23&_nc_ht=scontent.fnag7-1.fna&_nc_gid=OkqpLI7phlwlIGin8x9SwA&oh=00_AfdreH2dSCsjOHWv36IOtgjFaLESklIDBJ-QbUhT9YMSaw&oe=68E9AF50"
    },
    "id": "1858016665067022"
  },
  "service_models": [
    "SAAS"
  ],
  "solution_types": [
    "MESSAGING"
  ],
  "solution_subtypes": [],
  "__typename": "MarketingSolutionProvider"
}