{
  "company_website": "https://www.touchworks.com.br/",
  "countries": [
    "BR"
  ],
  "id": "7791151317591054",
  "name": "Touchworks Co",
  "description": "Transforme o atendimento da sua empresa através da IA em uma plataforma com uma abordagem AI-First. Nascido conversacional e adaptável às necessidades do seu negócio, a Touchworks permite que empresas de todos os tamanhos liberem o potencial do chatAI. Com um time de especialistas em automações, qualquer sistema pode ser integrado ao seu canal de atendimento.\n\nEscolha os especialistas na área! Nossa camada de serviço é composta por profissionais internos de IA conversacional de alto nível, renomados em grandes empresas globais.\n",
  "diverse_owned_identities": [],
  "facebook_platforms": [
    "WHATSAPP"
  ],
  "focus_areas": [
    "Automação de processos",
    "Chatbots",
    "Inteligencia artificial"
  ],
  "industries": [
    "ECOMMERCE",
    "FINANCIAL_SERVICES",
    "GOVERNMENT_AND_POLITICS",
    "ORGANIZATIONS_AND_ASSOCIATIONS",
    "PROFESSIONAL_SERVICES",
    "RETAIL",
    "TECHNOLOGY",
    "TELECOM",
    "TRAVEL"
  ],
  "is_badged": true,
  "language_tags": [
    "pt",
    "en",
    "es-419"
  ],
  "msp_profile_picture": {
    "image": {
      "uri": "https://scontent.fnag7-1.fna.fbcdn.net/v/t39.30808-6/486467270_1668917977350916_661981370018718909_n.jpg?stp=dst-jpg_s960x960_tt6&_nc_cat=107&ccb=1-7&_nc_sid=1e617a&_nc_ohc=5TVQ7NSj1ncQ7kNvwEvC7Ue&_nc_oc=AdkA0a03Fqai7vhSZcSoJcYDwpiuVT0TFDLGmAMiVLRsdsF50rAFlN8j-hoFZPyLzR8&_nc_zt=23&_nc_ht=scontent.fnag7-1.fna&_nc_gid=qhJod4b3ZJy8D5Xm29sldQ&oh=00_AfdGtoD7N1W6BhZHHzR2tzQgx1rOO7dbhJCrO2nO6j41-Q&oe=68E995D2"
    },
    "id": "1588344432074938"
  },
  "service_models": [
    "HOURLY",
    "SAAS",
    "PROJECT_BASED"
  ],
  "solution_types": [
    "MESSAGING"
  ],
  "solution_subtypes": [],
  "__typename": "MarketingSolutionProvider"
}